egrading_api/__init__.py
egrading_api/ai.py
egrading_api/auth.py
egrading_api/client.py
egrading_api/exams.py
egrading_api-0.1.0.dist-info/licenses/LICENSE
egrading_api-0.1.0.dist-info/METADATA
egrading_api-0.1.0.dist-info/WHEEL
egrading_api-0.1.0.dist-info/top_level.txt
egrading_api-0.1.0.dist-info/RECORD
