Metadata-Version: 2.4
Name: egrading-api
Version: 0.1.0
Summary: A Python wrapper for the ENSAM egrading platform
Home-page: https://github.com/NacreousDawn596/egrading-api
Author: Aferiad Kamal
Author-email: kamal@aferiad.xyz
Project-URL: Homepage, https://github.com/NacreousDawn596/egrading-api
Project-URL: Bug Tracker, https://github.com/NacreousDawn596/egrading-api/issues
Classifier: Programming Language :: Python :: 3
Classifier: License :: OSI Approved :: MIT License
Classifier: Operating System :: OS Independent
Requires-Python: >=3.6
License-File: LICENSE
Requires-Dist: requests
Requires-Dist: urllib3
Requires-Dist: g4f
Dynamic: author
Dynamic: author-email
Dynamic: home-page
Dynamic: license-file
Dynamic: requires-python
